{
  "valid_points": 41,
  "models": {
    "Constant": {
      "r2": 0.7,
      "params": [
        0.000887804539737802
      ]
    },
    "Linear": {
      "r2": 0.06838790431959407,
      "params": [
        1.7034522252003886e-07,
        0.0007172889720139391
      ]
    },
    "Quadratic": {
      "r2": 0.0522796232270486,
      "params": [
        7.192904162307277e-11,
        0.000790556403580399
      ]
    },
    "Cubic": {
      "r2": 0.04311840911139919,
      "params": [
        3.40150499932847e-14,
        0.0008179358242200322
      ]
    },
    "Logarithmic": {
      "r2": 0.11282530931352464,
      "params": [
        9.701957610148759e-05,
        0.00025626197275197167
      ]
    },
    "N Log N": {
      "r2": 0.06519591252287715,
      "params": [
        2.142179554556001e-08,
        0.0007352543672103978
      ]
    },
    "np": {
      "r2": -Infinity,
      "success": false
    }
  }
}