{
  "Constant": {
    "name": "Constant",
    "r2": 0.0,
    "bic": 556.0964023662182,
    "confidence_score": -0.09222198635284841,
    "params": [
      601.542622128017,
      172.52850504534166
    ],
    "order": 0
  },
  "Linear": {
    "name": "Linear",
    "r2": 0.6648252284752522,
    "bic": 512.3722752800448,
    "confidence_score": 0.5326032421224037,
    "params": [
      4.353584910482251,
      2.5155761839625773e-18
    ],
    "order": 2
  },
  "Quadratic": {
    "name": "Quadratic",
    "r2": 0.9159642477182757,
    "bic": 460.7247638887775,
    "confidence_score": 0.6976312681890031,
    "params": [
      0.014013674956888466,
      8.274566840824672e-20,
      1.932184050998768e-20
    ],
    "order": 4
  },
  "Cubic": {
    "name": "Cubic",
    "r2": 0.9937682067813649,
    "bic": 360.35051521274073,
    "confidence_score": 0.7093242340756681,
    "params": [
      3.883508385718e-05,
      1.2716195454092626e-22,
      5.327832763053188e-23,
      3.2339763017206094e-23
    ],
    "order": 5
  },
  "Logarithmic": {
    "name": "Logarithmic",
    "r2": 0.18857619754013977,
    "bic": 547.7378106226303,
    "confidence_score": 0.07635421118729135,
    "params": [
      169.98649053432487,
      8.427135403665687e-13
    ],
    "order": 1
  },
  "N Log N": {
    "name": "N Log N",
    "r2": 0.7299430667675084,
    "bic": 503.73150323068336,
    "confidence_score": 0.57772108041466,
    "params": [
      0.7745428165084292,
      5.932724735655244e-14
    ],
    "order": 3
  },
  "confidence_analysis": {
    "best_model": "Quadratic",
    "best_score": 0.6976312681890031,
    "second_best_model": "Quadratic",
    "second_best_score": 0.6976312681890031,
    "confidence_gap": 0.011692965886665019,
    "is_confident": false,
    "threshold": 0.03
  }
}