{
  "best_model": "O(n log n)",
  "details": {
    "O(1)": {
      "r2": 0,
      "aic": Infinity,
      "params_norm": [
        1.0
      ],
      "rss": 0.0
    },
    "O(n)": {
      "r2": 0,
      "aic": -2918.2768106062026,
      "params_norm": [
        -9.778793904550355e-10,
        1.0000000005923924
      ],
      "rss": 1.7354203008517e-14
    },
    "O(n^2)": {
      "r2": 0,
      "aic": -2710.238506058829,
      "params_norm": [
        -1.6370592904487226e-08,
        1.8986107378921625e-08,
        0.9999999954126015
      ],
      "rss": 2.2042749698553758e-13
    },
    "O(n^3)": {
      "r2": 0,
      "aic": -2599.2007698647712,
      "params_norm": [
        -1.58316306908492e-07,
        2.880903192393119e-07,
        -1.5917913911634305e-07,
        1.0000000258094672
      ],
      "rss": 8.447696598435734e-13
    },
    "O(log n)": {
      "r2": 0,
      "aic": -2895.482266545511,
      "params_norm": [
        -5.934146138113041e-10,
        0.999999999643905
      ],
      "rss": 2.2994357266520686e-14
    },
    "O(n log n)": {
      "r2": 0,
      "aic": -2978.499522047026,
      "params_norm": [
        -1.4129476602064176e-09,
        0.9999999996352317
      ],
      "rss": 8.251082968853099e-15
    },
    "O(2^n)": {
      "r2": 0,
      "aic": -2934.0134064217073,
      "params_norm": [
        0.9999999994674227,
        8.876288830373813e-10
      ],
      "rss": 1.4289939592839143e-14
    }
  }
}