{
  "best_model": "O(2^n)",
  "details": {
    "O(1)": {
      "r2": 0,
      "aic": Infinity,
      "params_norm": [
        1.0
      ],
      "rss": 0.0
    },
    "O(n)": {
      "r2": 0,
      "aic": -3509.245031116476,
      "params_norm": [
        3.539513381405014e-10,
        0.9999999997936918
      ],
      "rss": 7.889203539065576e-14
    },
    "O(n^2)": {
      "r2": 0,
      "aic": -2974.2473113547344,
      "params_norm": [
        2.262728146446774e-08,
        -2.697387986981183e-08,
        1.000000006707853
      ],
      "rss": 1.5429677741050748e-11
    },
    "O(n^3)": {
      "r2": 0,
      "aic": -2919.1748556581533,
      "params_norm": [
        9.207473059506364e-09,
        1.2993395631032284e-08,
        -2.4496106730549883e-08,
        1.0000000064036458
      ],
      "rss": 2.605180241202014e-11
    },
    "O(log n)": {
      "r2": 0,
      "aic": -3049.2354421366986,
      "params_norm": [
        -1.7262467729194512e-09,
        0.9999999988883356
      ],
      "rss": 7.499792729499622e-12
    },
    "O(n log n)": {
      "r2": 0,
      "aic": -3478.2221994554584,
      "params_norm": [
        9.149493385152141e-10,
        1.000000000238507
      ],
      "rss": 1.0725798703846486e-13
    },
    "O(2^n)": {
      "r2": 0,
      "aic": -3687.650833246638,
      "params_norm": [
        1.0000000000853677,
        -1.463447165138362e-10
      ],
      "rss": 1.348645969605902e-14
    },
    "O(n^k)": {
      "r2": 0,
      "aic": -3387.9355236393153,
      "params_norm": [
        0.999999999792065,
        -3.2278032427202367e-10
      ],
      "rss": 2.622149296354773e-13
    }
  }
}