{
  "valid_points": 41,
  "models": {
    "Constant": {
      "r2": 0.7,
      "params": [
        0.00011943502169897702
      ]
    },
    "Linear": {
      "r2": 0.04898979676670079,
      "params": [
        -5.219422227753512e-09,
        0.00012465966325636568
      ]
    },
    "Quadratic": {
      "r2": 0.02306374074667006,
      "params": [
        -1.7295463186432625e-12,
        0.0001217733700515535
      ]
    },
    "Cubic": {
      "r2": 0.01049681625089105,
      "params": [
        -6.075722238536175e-16,
        0.00012068300724896961
      ]
    },
    "Logarithmic": {
      "r2": 0.013180608535301563,
      "params": [
        -1.2004750137539149e-06,
        0.0001272494350355324
      ]
    },
    "N Log N": {
      "r2": 0.045184010023147536,
      "params": [
        -6.456057532913038e-10,
        0.00012403254801845735
      ]
    },
    "np": {
      "r2": -Infinity,
      "success": false
    }
  }
}