{
  "Constant": {
    "name": "Constant",
    "r2": 0.0,
    "bic": 173.3680412153595,
    "confidence_score": -0.09572595157174699,
    "params": [
      8.89094245814972,
      1.157697766545101
    ],
    "order": 0
  },
  "Linear": {
    "name": "Linear",
    "r2": 0.870803492952297,
    "bic": 95.60405373248307,
    "confidence_score": 0.7350775413805499,
    "params": [
      0.05373960595346596,
      2.1856448568881453e-19
    ],
    "order": 2
  },
  "Quadratic": {
    "name": "Quadratic",
    "r2": 0.999952776185657,
    "bic": -201.4976381798796,
    "confidence_score": 0.7763638488280366,
    "params": [
      0.00015764940956639585,
      0.0022942603074773754,
      0.29743763766844755
    ],
    "order": 4
  },
  "Cubic": {
    "name": "Cubic",
    "r2": 0.9999527761849697,
    "bic": -197.86005146705855,
    "confidence_score": 0.7085008730414758,
    "params": [
      8.24253626735046e-16,
      0.00015764940903154802,
      0.0022942603994963767,
      0.29743763444263843
    ],
    "order": 5
  },
  "Logarithmic": {
    "name": "Logarithmic",
    "r2": 0.3006666935692115,
    "bic": 159.77818416317126,
    "confidence_score": 0.18494074199746452,
    "params": [
      2.1826081427314405,
      4.847730753958232e-23
    ],
    "order": 1
  },
  "N Log N": {
    "name": "N Log N",
    "r2": 0.9240931495026221,
    "bic": 75.39460422806113,
    "confidence_score": 0.768367197930875,
    "params": [
      0.009496854707872553,
      6.090006188306211e-28
    ],
    "order": 3
  },
  "confidence_analysis": {
    "best_model": "Quadratic",
    "best_score": 0.7763638488280366,
    "second_best_model": "N Log N",
    "second_best_score": 0.768367197930875,
    "confidence_gap": 0.007996650897161506,
    "is_confident": false,
    "threshold": 0.03
  }
}