{
  "best_model": "O(2^n)",
  "details": {
    "O(1)": {
      "r2": 0,
      "aic": Infinity,
      "params_norm": [
        1.0
      ],
      "rss": 0.0
    },
    "O(n)": {
      "r2": 0,
      "aic": -3697.4675907558712,
      "params_norm": [
        3.539513381405014e-10,
        0.9999999997936918
      ],
      "rss": 1.2237323412690717e-14
    },
    "O(n^2)": {
      "r2": 0,
      "aic": -3162.469884673309,
      "params_norm": [
        2.262728146446774e-08,
        -2.697387986981183e-08,
        1.000000006707853
      ],
      "rss": 2.39337127205344e-12
    },
    "O(n^3)": {
      "r2": 0,
      "aic": -3107.3974289145294,
      "params_norm": [
        9.207473059506364e-09,
        1.2993395631032284e-08,
        -2.4496106730549883e-08,
        1.0000000064036458
      ],
      "rss": 4.041019946298185e-12
    },
    "O(log n)": {
      "r2": 0,
      "aic": -3237.4580154140217,
      "params_norm": [
        -1.7262467729194512e-09,
        0.9999999988883356
      ],
      "rss": 1.1633287988066845e-12
    },
    "O(n log n)": {
      "r2": 0,
      "aic": -3666.4447764002716,
      "params_norm": [
        9.149493385152141e-10,
        1.000000000238507
      ],
      "rss": 1.6637299881933573e-14
    },
    "O(2^n)": {
      "r2": 0,
      "aic": -3875.873401849454,
      "params_norm": [
        1.0000000000853677,
        -1.463447165138362e-10
      ],
      "rss": 2.0919495045230126e-15
    },
    "O(n^k)": {
      "r2": 0,
      "aic": -3576.1580887137916,
      "params_norm": [
        0.999999999792065,
        -3.2278032427202367e-10
      ],
      "rss": 4.067341790614675e-14
    }
  }
}