{
  "record_index": 17,
  "original_code": "l, r = map(int, input().split())\n\nif l == r:\n    print(0)\n    exit()\nbinr, binl = bin(r)[2:], bin(l)[2:]\nbinl = '0' * (len(binr) - len(binl)) + binl\n# print(binl, binr)\nfor i in range(len(binl)):\n    if binl[i] != binr[i]:\n        binl = '1' * len(binl[i:])\n        break\n\nprint(int(binl, 2))\n",
  "modified_code": "def generate_input(n):\n    if n <= 0:\n        l, r = 0, 0\n    elif n == 1:\n        l, r = 0, 1\n    elif n <= 5:\n        l, r = 1, 3\n    else:\n        shift = min(n, 60)\n        l = 1 << (shift - 1)\n        r = (1 << shift) - 1\n    return f\"{l} {r}\"\n\ntry:\n    n  # check if n is defined in the environment\nexcept NameError:\n    n = 0\n\nl, r = map(int, generate_input(n).split())\n\nif l == r:\n    print(0)\n    exit()\nbinr, binl = bin(r)[2:], bin(l)[2:]\nbinl = '0' * (len(binr) - len(binl)) + binl\n# print(binl, binr)\nfor i in range(len(binl)):\n    if binl[i] != binr[i]:\n        binl = '1' * len(binl[i:])\n        break\n\nprint(int(binl, 2))",
  "execution_results": {
    "10": 0.00025128000415861604,
    "100": 0.00029979998944327233,
    "1000": 0.0004160800133831799,
    "10000": 0.00043446000199764967,
    "100000": 0.00020735999569296837
  },
  "complexity_analysis": {
    "best_fit": "O(n log n)",
    "best_r_squared": 0.3556806911090663,
    "n_values": [
      10,
      100,
      1000,
      10000,
      100000
    ],
    "actual_times": [
      0.00025128000415861604,
      0.00029979998944327233,
      0.0004160800133831799,
      0.00043446000199764967,
      0.00020735999569296837
    ],
    "all_fits": {
      "O(1)": {
        "params": [
          0.0003217960009351373
        ],
        "r_squared": -12.900678378024185,
        "predicted_times": [
          0,
          0,
          0,
          0,
          0
        ]
      },
      "O(log n)": {
        "params": [
          2.033365046976237e-06,
          0.00030775001279931844
        ],
        "r_squared": 0.005461903162196857,
        "predicted_times": [
          0.00031243200884510105,
          0.00031711400489088366,
          0.0003217960009366663,
          0.0003264779969824489,
          0.00033115999302823156
        ]
      },
      "O(n)": {
        "params": [
          -1.3398432178264362e-09,
          0.0003515699969213968
        ],
        "r_squared": 0.3413683464655416,
        "predicted_times": [
          0.00035155659848921857,
          0.00035143601259961417,
          0.00035023015370357036,
          0.0003381715647431325,
          0.00021758567513875318
        ]
      },
      "O(n log n)": {
        "params": [
          -1.1823685657062038e-10,
          0.00035137383143220296
        ],
        "r_squared": 0.3556806911090663,
        "predicted_times": [
          0.00035137110892796914,
          0.0003513193813475266,
          0.000350557080162057,
          0.00034048381449692356,
          0.00021524861974121017
        ]
      },
      "O(n²)": {
        "params": [
          -1.562094151697894e-13,
          1.4554221609046802e-08,
          0.00031394666440796626
        ],
        "r_squared": -44.154324495903694,
        "predicted_times": [
          0.0003140921910031152,
          0.00031540052447471927,
          0.0003283446766018433,
          0.00044386793898145533,
          0.001549103332577816
        ]
      },
      "O(n³)": {
        "params": [
          1.5012319361231513e-16,
          -1.67077739855546e-11,
          1.6896455185792448e-07,
          0.00026545106899031443
        ],
        "r_squared": -1086.4836022266923,
        "predicted_times": [
          0.0002671390438816183,
          0.00028218059655944495,
          0.0004178579700562966,
          0.0002842099924103337,
          -0.0063973776497236725
        ]
      },
      "O(2^n)": {
        "params": [
          1.0,
          1.0
        ],
        "r_squared": -Infinity,
        "predicted_times": [
          22026.465794806718,
          2.6881171418161356e+43,
          Infinity,
          Infinity,
          Infinity
        ]
      }
    }
  }
}