{
  "record_index": 16,
  "original_code": "l, r = map(int, input().split())\n\nif l == r:\n    print(0)\n    exit()\nbinr, binl = bin(r)[2:], bin(l)[2:]\nbinl = '0' * (len(binr) - len(binl)) + binl\n# print(binl, binr)\nfor i in range(len(binl)):\n    if binl[i] != binr[i]:\n        binl = '1' * len(binl[i:])\n        break\n\nprint(int(binl, 2))\n",
  "modified_code": "def generate_input(n):\n    if n <= 0:\n        return \"0 0\"\n    l = n\n    r = n * 2\n    if l > r:\n        l, r = r, l\n    return f\"{l} {r}\"\n\nn = 1\nl, r = map(int, generate_input(n).split())\n\nif l == r:\n    print(0)\n    exit()\nbinr, binl = bin(r)[2:], bin(l)[2:]\nbinl = '0' * (len(binr) - len(binl)) + binl\n# print(binl, binr)\nfor i in range(len(binl)):\n    if binl[i] != binr[i]:\n        binl = '1' * len(binl[i:])\n        break\n\nprint(int(binl, 2))",
  "execution_results": {
    "10": 0.0003055000095628202,
    "100": 0.00021638000616803766,
    "1000": 0.00020585999591276049,
    "10000": 0.0002075200085528195,
    "100000": 0.00020755999721586705
  },
  "complexity_analysis": {
    "best_fit": "O(log n)",
    "best_r_squared": 0.5613764339658049,
    "n_values": [
      10,
      100,
      1000,
      10000,
      100000
    ],
    "actual_times": [
      0.0003055000095628202,
      0.00021638000616803766,
      0.00020585999591276049,
      0.0002075200085528195,
      0.00020755999721586705
    ],
    "all_fits": {
      "O(1)": {
        "params": [
          0.00022856400348246099
        ],
        "r_squared": -34.981172181713,
        "predicted_times": [
          0,
          0,
          0,
          0,
          0
        ]
      },
      "O(log n)": {
        "params": [
          -8.89174611228296e-06,
          0.00028998600954701124
        ],
        "r_squared": 0.5613764339658049,
        "predicted_times": [
          0.00026951200749818075,
          0.0002490380054493502,
          0.00022856400340051972,
          0.00020809000135168924,
          0.00018761599930285872
        ]
      },
      "O(n)": {
        "params": [
          -3.0581984230878573e-10,
          0.00023535993201828404
        ],
        "r_squared": 0.09559033782822268,
        "predicted_times": [
          0.00023535687381986094,
          0.00023532935003405317,
          0.00023505411217597524,
          0.00023230173359519617,
          0.00020477794778740548
        ]
      },
      "O(n log n)": {
        "params": [
          -2.573729927292356e-11,
          0.00023500238063004793
        ],
        "r_squared": 0.09058320916023521,
        "predicted_times": [
          0.00023500178800683153,
          0.00023499052816571998,
          0.00023482459366512865,
          0.00023263188776445753,
          0.0002053712198101678
        ]
      },
      "O(n²)": {
        "params": [
          4.2718316748236935e-14,
          -4.652342066594776e-09,
          0.00024564871910040634
        ],
        "r_squared": -17.788423728341996,
        "predicted_times": [
          0.00024560219995157205,
          0.0002451839120769143,
          0.0002410390953505598,
          0.00020339713010928228,
          -0.00015934986682439528
        ]
      },
      "O(n³)": {
        "params": [
          -6.635875336187279e-17,
          7.358984141542872e-12,
          -7.290613257161326e-08,
          0.00026708516167860363
        ],
        "r_squared": -1325.2264361221355,
        "predicted_times": [
          0.0002663568361849429,
          0.0002598680719041044,
          0.00020147165449517138,
          0.0002739705181446552,
          0.003353222442266091
        ]
      },
      "O(2^n)": {
        "params": [
          1.0,
          1.0
        ],
        "r_squared": -Infinity,
        "predicted_times": [
          22026.465794806718,
          2.6881171418161356e+43,
          Infinity,
          Infinity,
          Infinity
        ]
      }
    }
  }
}